Metadata-Version: 2.1
Name: motivatememore
Version: 0.0.1
Summary: a Python module to motivate you
Home-page: UNKNOWN
Author: Francisco Gutierrez
Author-email: franciscocw0101@gmail.com
License: UNKNOWN
Keywords: motivation,learning
Platform: UNKNOWN
Classifier: Development Status :: 3 - Alpha
Classifier: Intended Audience :: Education
Classifier: Programming Language :: Python :: 3
